sphinx_confluence/__init__.py
sphinx_confluence/themes/confluence/layout.html
sphinx_confluence/themes/confluence/theme.conf
sphinx_confluence-0.0.4.dist-info/LICENSE
sphinx_confluence-0.0.4.dist-info/METADATA
sphinx_confluence-0.0.4.dist-info/WHEEL
sphinx_confluence-0.0.4.dist-info/top_level.txt
sphinx_confluence-0.0.4.dist-info/RECORD
