Metadata-Version: 2.1
Name: sphinx-confluence
Version: 0.0.4
Summary: Atlassian Confluence extension for sphinx
Home-page: https://github.com/Arello-Mobile/sphinx-confluence
Author: Arello Mobile
License: MIT
Platform: UNKNOWN
Classifier: Development Status :: 4 - Beta
Classifier: Environment :: Console
Classifier: Intended Audience :: Developers
Classifier: License :: OSI Approved :: MIT License
Classifier: Operating System :: OS Independent
Classifier: Programming Language :: Python
Classifier: Programming Language :: Python :: 2.7
Classifier: Programming Language :: Python :: 3.4
Classifier: Programming Language :: Python :: 3.5
Requires-Dist: Sphinx (>=1.3.5)
Requires-Dist: docutils (==0.12)
